PaddockTS/__init__.py
PaddockTS/filter.py
PaddockTS/get_outputs.py
PaddockTS/query.py
PaddockTS/utils.py
PaddockTS/Data/__init__.py
PaddockTS/Data/download_ds2.py
PaddockTS/Data/environmental.py
PaddockTS/IndicesAndVegFrac/__init__.py
PaddockTS/IndicesAndVegFrac/add_indices_and_veg_frac.py
PaddockTS/IndicesAndVegFrac/indices.py
PaddockTS/IndicesAndVegFrac/utils.py
PaddockTS/IndicesAndVegFrac/veg_frac.py
PaddockTS/PaddockSegmentation/_1_presegment.py
PaddockTS/PaddockSegmentation/_2_segment.py
PaddockTS/PaddockSegmentation/__init__.py
PaddockTS/PaddockSegmentation/get_paddocks.py
PaddockTS/PaddockSegmentation/utils.py
PaddockTS/PaddockTS/__init__.py
PaddockTS/PaddockTS/get_paddock_ts.py
PaddockTS/Plotting/checkpoint_plots.py
PaddockTS/Plotting/plotting_functions.py
PaddockTS/Plotting/topographic_plots.py
paddockts-0.7.0.dist-info/METADATA
paddockts-0.7.0.dist-info/WHEEL
paddockts-0.7.0.dist-info/top_level.txt
paddockts-0.7.0.dist-info/RECORD
