Metadata-Version: 2.4
Name: PaddockTS
Version: 0.7.0
Summary: Vegetation fractional cover estimates via a TensorFlow-trained MLP model
Author: Borevitz Labs Australian National University
Author-email: Yasar Adeel Ansari <u6737670@anu.edu.au>
License: MIT
Requires-Python: >=3.8
Requires-Dist: numpy<2
Requires-Dist: tensorflow; sys_platform == "darwin"
Requires-Dist: tflite_runtime; sys_platform != "darwin"
Requires-Dist: dataclasses-json
Requires-Dist: typing_extensions
